vat_algorithms/VAT.py
vat_algorithms/__init__.py
vat_algorithms/iVAT.py
vat_algorithms-1.0.3.dist-info/METADATA
vat_algorithms-1.0.3.dist-info/WHEEL
vat_algorithms-1.0.3.dist-info/licenses/LICENSE
vat_algorithms-1.0.3.dist-info/RECORD
